MANIFEST.in
board_purchase_view.xml
purchase_double_validation_installer.xml
purchase_double_validation_view.xml
purchase_double_validation_workflow.xml
setup.py
./__init__.py
./__openerp__.py
./purchase_double_validation_installer.py
i18n/ar.po
i18n/bg.po
i18n/bs.po
i18n/ca.po
i18n/cs.po
i18n/da.po
i18n/de.po
i18n/es.po
i18n/es_CR.po
i18n/es_EC.po
i18n/es_MX.po
i18n/es_PE.po
i18n/es_VE.po
i18n/fi.po
i18n/fr.po
i18n/gl.po
i18n/hr.po
i18n/hu.po
i18n/it.po
i18n/ja.po
i18n/lt.po
i18n/mk.po
i18n/mn.po
i18n/nl.po
i18n/pl.po
i18n/pt.po
i18n/pt_BR.po
i18n/purchase_double_validation.pot
i18n/ro.po
i18n/ru.po
i18n/sl.po
i18n/sv.po
i18n/tr.po
i18n/zh_CN.po
images/purchase_validation.jpeg
openerp_purchase_double_validation.egg-info/PKG-INFO
openerp_purchase_double_validation.egg-info/SOURCES.txt
openerp_purchase_double_validation.egg-info/dependency_links.txt
openerp_purchase_double_validation.egg-info/requires.txt
openerp_purchase_double_validation.egg-info/top_level.txt
test/purchase_double_validation_demo.yml
test/purchase_double_validation_test.yml